cleandups/__init__.py
cleandups/__main__.py
cleandups/cleandups.py
cleandups-0.1.0.dist-info/licenses/LICENSE
cleandups-0.1.0.dist-info/METADATA
cleandups-0.1.0.dist-info/WHEEL
cleandups-0.1.0.dist-info/entry_points.txt
cleandups-0.1.0.dist-info/top_level.txt
cleandups-0.1.0.dist-info/RECORD
