Metadata-Version: 2.4
Name: cleandups
Version: 0.1.0
Summary: Инструмент для поиска и удаления дубликатов файлов
Home-page: https://github.com/Flaymie/cleandups
Author: Flaymie
Author-email: funquenop@gmail.com
Classifier: Programming Language :: Python :: 3
Classifier: License :: OSI Approved :: MIT License
Classifier: Operating System :: OS Independent
Requires-Python: >=3.6
License-File: LICENSE
Requires-Dist: send2trash>=1.8.0
Dynamic: author
Dynamic: author-email
Dynamic: classifier
Dynamic: description
Dynamic: description-content-type
Dynamic: home-page
Dynamic: license-file
Dynamic: requires-dist
Dynamic: requires-python
Dynamic: summary
